physalia/__init__.py
physalia/analytics.py
physalia/asserts.py
physalia/cli.py
physalia/energy_profiler.py
physalia/exceptions.py
physalia/models.py
physalia/power_meters.py
physalia/fixtures/__init__.py
physalia/fixtures/models.py
physalia/tests/__init__.py
physalia/tests/test_analytics.py
physalia/tests/test_asserts.py
physalia/tests/test_energy_profiler.py
physalia/tests/test_models.py
physalia/tests/test_power_meters.py
physalia/tests/baseline_images/violinplot.png
physalia/third_party/__init__.py
physalia/third_party/monsoon.py
physalia/third_party/monsoon_async.py
physalia/utils/__init__.py
physalia/utils/android.py
physalia/utils/monsoon.py
physalia/utils/symbols.py
physalia-0.0.1.dev113.dist-info/DESCRIPTION.rst
physalia-0.0.1.dev113.dist-info/METADATA
physalia-0.0.1.dev113.dist-info/RECORD
physalia-0.0.1.dev113.dist-info/WHEEL
physalia-0.0.1.dev113.dist-info/entry_points.txt
physalia-0.0.1.dev113.dist-info/metadata.json
physalia-0.0.1.dev113.dist-info/pbr.json
physalia-0.0.1.dev113.dist-info/top_level.txt
