Metadata-Version: 2.0
Name: physalia
Version: 0.0.1.dev113
Summary: Test suite for energy consumption
Home-page: https://luiscruz.github.io/
Author: Luis Cruz
Author-email: luismirandacruz@gmail.com
License: MIT
Platform: UNKNOWN
Classifier: Development Status :: 4 - Beta
Classifier: Environment :: Console
Classifier: Environment :: Plugins
Classifier: Intended Audience :: Science/Research
Classifier: Intended Audience :: Developers
Classifier: Intended Audience :: Information Technology
Classifier: Operating System :: OS Independent
Classifier: Programming Language :: Python
Classifier: License :: OSI Approved :: MIT License
Classifier: Topic :: Software Development :: Quality Assurance
Classifier: Topic :: Software Development :: Testing
Classifier: Topic :: System :: Benchmark
Requires-Dist: click
Requires-Dist: matplotlib
Requires-Dist: mobly
Requires-Dist: numpy
Requires-Dist: pylatexenc
Requires-Dist: pyserial
Requires-Dist: python-gflags
Requires-Dist: scipy
Requires-Dist: statsmodels
Requires-Dist: tabulate
Requires-Dist: timeout-decorator
Requires-Dist: whichcraft
